_webrtcvad.cpython-313-aarch64-linux-gnu.so
webrtcvad.py
webrtcvad_wheels-2.0.14.dist-info/LICENSE
webrtcvad_wheels-2.0.14.dist-info/METADATA
webrtcvad_wheels-2.0.14.dist-info/top_level.txt
webrtcvad_wheels-2.0.14.dist-info/RECORD
webrtcvad_wheels-2.0.14.dist-info/WHEEL
