Metadata-Version: 2.1
Name: webrtcvad-wheels
Version: 2.0.14
Summary: Python interface to the Google WebRTC Voice Activity Detector (VAD) [released with binary wheels!]
Home-page: https://github.com/daanzu/py-webrtcvad-wheels
Author: David Zurow
Author-email: daanzu@gmail.com
License: MIT
Keywords: speechrecognition asr voiceactivitydetection vad webrtc
Classifier: Development Status :: 5 - Production/Stable
Classifier: Intended Audience :: Developers
Classifier: Topic :: Scientific/Engineering :: Artificial Intelligence
Classifier: Topic :: Scientific/Engineering :: Information Analysis
Classifier: Topic :: Scientific/Engineering :: Human Machine Interfaces
Classifier: License :: OSI Approved :: MIT License
Classifier: Programming Language :: Python :: 3.6
Classifier: Programming Language :: Python :: 3.7
Classifier: Programming Language :: Python :: 3.8
Classifier: Programming Language :: Python :: 3.9
Classifier: Programming Language :: Python :: 3.10
Classifier: Programming Language :: Python :: 3.11
Classifier: Programming Language :: Python :: 3.12
Classifier: Programming Language :: Python :: 3.13
License-File: LICENSE
Provides-Extra: dev
Requires-Dist: unittest2; extra == "dev"
Requires-Dist: psutil; extra == "dev"
